accounting/__init__.py
accounting/apps.py
accounting/migrations/0001_initial.py
accounting/migrations/0002_account_system_id.py
accounting/migrations/0003_accountheading_system_id_currency_system_id.py
accounting/migrations/0004_account_tag_alter_accountingentry_currency.py
accounting/migrations/0005_alter_accountingentry_description.py
accounting/migrations/__init__.py
accounting/models/__init__.py
accounting/models/common.py
accounting/serializers/__init__.py
django_double_entry-1.0.9.dist-info/METADATA
django_double_entry-1.0.9.dist-info/WHEEL
django_double_entry-1.0.9.dist-info/licenses/AUTHORS.rst
django_double_entry-1.0.9.dist-info/licenses/LICENCE
django_double_entry-1.0.9.dist-info/RECORD
